xontrib/cheatsheet.py
xontrib_cheatsheet-0.4.4.dist-info/LICENSE
xontrib_cheatsheet-0.4.4.dist-info/METADATA
xontrib_cheatsheet-0.4.4.dist-info/WHEEL
xontrib_cheatsheet-0.4.4.dist-info/top_level.txt
xontrib_cheatsheet-0.4.4.dist-info/RECORD
