Metadata-Version: 2.1
Name: xontrib-cheatsheet
Version: 0.4.4
Summary: Cheat sheet for xonsh shell with copy-pastable examples.
Home-page: https://github.com/anki-code/xontrib-cheatsheet
Author: anki-code
Author-email: no@no.no
License: MIT
Project-URL: Documentation, https://github.com/anki-code/xontrib-cheatsheet/blob/master/README.md
Project-URL: Code, https://github.com/anki-code/xontrib-cheatsheet
Project-URL: Issue tracker, https://github.com/anki-code/xontrib-cheatsheet/issues
Platform: any
Classifier: Programming Language :: Python :: 3
Classifier: License :: OSI Approved :: MIT License
Classifier: Operating System :: OS Independent
Classifier: Topic :: System :: Shells
Classifier: Topic :: System :: System Shells
Classifier: Topic :: Terminals
Requires-Python: >=3.6
License-File: LICENSE
Requires-Dist: xonsh
